vicinity/__init__.py
vicinity/datatypes.py
vicinity/py.typed
vicinity/utils.py
vicinity/version.py
vicinity/vicinity.py
vicinity/backends/__init__.py
vicinity/backends/annoy.py
vicinity/backends/base.py
vicinity/backends/basic.py
vicinity/backends/faiss.py
vicinity/backends/hnsw.py
vicinity/backends/pynndescent.py
vicinity/backends/usearch.py
vicinity/backends/voyager.py
vicinity/integrations/dataset_card_template.md
vicinity/integrations/huggingface.py
vicinity-0.4.2.dist-info/METADATA
vicinity-0.4.2.dist-info/WHEEL
vicinity-0.4.2.dist-info/top_level.txt
vicinity-0.4.2.dist-info/RECORD
