Metadata-Version: 2.4
Name: vicinity
Version: 0.4.2
Summary: Lightweight Nearest Neighbors with Flexible Backends
Author-email: Stéphan Tulkens <stephantul@gmail.com>, Thomas van Dongen <thomas123@live.nl>
License: MIT License
Project-URL: Homepage, https://github.com/MinishLab
Project-URL: Bug Reports, https://github.com/MinishLab/vicinity/issues
Project-URL: Source, https://github.com/MinishLab/vicinity
Classifier: Development Status :: 4 - Beta
Classifier: Intended Audience :: Developers
Classifier: Intended Audience :: Science/Research
Classifier: Topic :: Scientific/Engineering :: Artificial Intelligence
Classifier: Topic :: Software Development :: Libraries
Classifier: License :: OSI Approved :: MIT License
Classifier: Programming Language :: Python :: 3 :: Only
Classifier: Programming Language :: Python :: 3.9
Classifier: Programming Language :: Python :: 3.10
Classifier: Programming Language :: Python :: 3.11
Classifier: Programming Language :: Python :: 3.12
Requires-Python: >=3.9
Requires-Dist: numpy
Requires-Dist: orjson
Requires-Dist: tqdm
Provides-Extra: dev
Requires-Dist: black; extra == "dev"
Requires-Dist: ipython; extra == "dev"
Requires-Dist: mypy; extra == "dev"
Requires-Dist: pre-commit; extra == "dev"
Requires-Dist: pytest; extra == "dev"
Requires-Dist: pytest-coverage; extra == "dev"
Requires-Dist: ruff; extra == "dev"
Requires-Dist: setuptools; extra == "dev"
Provides-Extra: huggingface
Requires-Dist: datasets; extra == "huggingface"
Provides-Extra: integrations
Requires-Dist: datasets; extra == "integrations"
Provides-Extra: hnsw
Requires-Dist: hnswlib; extra == "hnsw"
Provides-Extra: pynndescent
Requires-Dist: pynndescent>=0.5.10; extra == "pynndescent"
Requires-Dist: numba>=0.59.0; extra == "pynndescent"
Requires-Dist: llvmlite>=0.42.0; extra == "pynndescent"
Requires-Dist: numpy>=1.24.0; extra == "pynndescent"
Provides-Extra: annoy
Requires-Dist: annoy; extra == "annoy"
Provides-Extra: faiss
Requires-Dist: faiss-cpu; extra == "faiss"
Provides-Extra: usearch
Requires-Dist: usearch; extra == "usearch"
Provides-Extra: voyager
Requires-Dist: voyager; extra == "voyager"
Provides-Extra: backends
Requires-Dist: hnswlib; extra == "backends"
Requires-Dist: pynndescent>=0.5.10; extra == "backends"
Requires-Dist: numba>=0.59.0; extra == "backends"
Requires-Dist: llvmlite>=0.42.0; extra == "backends"
Requires-Dist: numpy>=1.24.0; extra == "backends"
Requires-Dist: annoy; extra == "backends"
Requires-Dist: faiss-cpu; extra == "backends"
Requires-Dist: usearch; extra == "backends"
Requires-Dist: voyager; extra == "backends"
Provides-Extra: all
Requires-Dist: datasets; extra == "all"
Requires-Dist: hnswlib; extra == "all"
Requires-Dist: pynndescent>=0.5.10; extra == "all"
Requires-Dist: numba>=0.59.0; extra == "all"
Requires-Dist: llvmlite>=0.42.0; extra == "all"
Requires-Dist: numpy>=1.24.0; extra == "all"
Requires-Dist: annoy; extra == "all"
Requires-Dist: faiss-cpu; extra == "all"
Requires-Dist: usearch; extra == "all"
Requires-Dist: voyager; extra == "all"
